staticpipes/__init__.py
staticpipes/build_directory.py
staticpipes/check_base.py
staticpipes/check_report.py
staticpipes/cli.py
staticpipes/collection.py
staticpipes/collection_base.py
staticpipes/config.py
staticpipes/current_info.py
staticpipes/directory_base.py
staticpipes/exceptions.py
staticpipes/jinja2_environment.py
staticpipes/pipe_base.py
staticpipes/process_base.py
staticpipes/process_current_info.py
staticpipes/serve.py
staticpipes/source_directory.py
staticpipes/utils.py
staticpipes/watcher.py
staticpipes/worker.py
staticpipes/worker_storage.py
staticpipes/checks/__init__.py
staticpipes/checks/html_tags.py
staticpipes/checks/html_with_tidy.py
staticpipes/checks/internal_links.py
staticpipes/pipes/__init__.py
staticpipes/pipes/collection_records_process.py
staticpipes/pipes/copy.py
staticpipes/pipes/copy_with_versioning.py
staticpipes/pipes/css_minifier.py
staticpipes/pipes/exclude_dot_directories.py
staticpipes/pipes/exclude_underscore_directories.py
staticpipes/pipes/javascript_minifier.py
staticpipes/pipes/jinja2.py
staticpipes/pipes/load_collection_csv.py
staticpipes/pipes/load_collection_json_list.py
staticpipes/pipes/load_collection_python_docs.py
staticpipes/pipes/process.py
staticpipes/processes/__init__.py
staticpipes/processes/change_extension.py
staticpipes/processes/css_minifier.py
staticpipes/processes/javascript_minifier.py
staticpipes/processes/jinja2.py
staticpipes/processes/jinja2_render_contents.py
staticpipes/processes/jinja2_render_source_file.py
staticpipes/processes/markdown_yaml_to_html_context.py
staticpipes/processes/remove_html_extension.py
staticpipes/processes/version.py
staticpipes-0.6.0.dist-info/licenses/LICENSE.txt
staticpipes-0.6.0.dist-info/METADATA
staticpipes-0.6.0.dist-info/WHEEL
staticpipes-0.6.0.dist-info/top_level.txt
staticpipes-0.6.0.dist-info/RECORD
