Metadata-Version: 2.4
Name: staticpipes
Version: 0.6.0
Summary: StaticPipes, the flexible and extendable static site website generator in Python
Project-URL: Homepage, https://github.com/StaticPipes/StaticPipes
Project-URL: Repository, https://github.com/StaticPipes/StaticPipes
Project-URL: Issues, https://github.com/StaticPipes/StaticPipes/issues
Project-URL: Changelog, https://github.com/StaticPipes/StaticPipes/blob/main/CHANGELOG.md
Requires-Python: >=3.10
License-File: LICENSE.txt
Provides-Extra: allbuild
Requires-Dist: rjsmin; extra == "allbuild"
Requires-Dist: rcssmin; extra == "allbuild"
Requires-Dist: jinja2; extra == "allbuild"
Requires-Dist: markdown-it-py; extra == "allbuild"
Requires-Dist: pyyaml; extra == "allbuild"
Provides-Extra: dev
Requires-Dist: watchdog; extra == "dev"
Provides-Extra: staticpipesdev
Requires-Dist: pytest; extra == "staticpipesdev"
Requires-Dist: black; extra == "staticpipesdev"
Requires-Dist: isort; extra == "staticpipesdev"
Requires-Dist: mypy; extra == "staticpipesdev"
Requires-Dist: flake8; extra == "staticpipesdev"
Requires-Dist: sphinx; extra == "staticpipesdev"
Dynamic: license-file
